<?xml version="1.0"?><h:html xmlns="http://www.w3.org/2002/xforms" xmlns:ev="http://www.w3.org/2001/xml-events" xmlns:h="http://www.w3.org/1999/xhtml" xmlns:jr="http://openrosa.org/javarosa" xmlns:odk="http://www.opendatakit.org/xforms" xmlns:orx="http://openrosa.org/xforms" xmlns:xsd="http://www.w3.org/2001/XMLSchema"><h:head><h:title>OSCE_Essential Newborn care</h:title><model odk:xforms-version="1.0.0"><instance><data id="osce1_form" version="1.1"><intro><reserved_name_for_field_list_labels_3/><step1/><step2/><step3/><step4/><step5/><step6/><step7/><step8/><step9/><step10/><step11/></intro><meta><instanceID/></meta></data></instance><bind nodeset="/data/intro/reserved_name_for_field_list_labels_3" type="string"/><bind nodeset="/data/intro/step1" required="true()" type="string"/><bind nodeset="/data/intro/step2" required="true()" type="string"/><bind nodeset="/data/intro/step3" required="true()" type="string"/><bind nodeset="/data/intro/step4" required="true()" type="string"/><bind nodeset="/data/intro/step5" required="true()" type="string"/><bind nodeset="/data/intro/step6" required="true()" type="string"/><bind nodeset="/data/intro/step7" required="true()" type="string"/><bind nodeset="/data/intro/step8" required="true()" type="string"/><bind nodeset="/data/intro/step9" required="true()" type="string"/><bind nodeset="/data/intro/step10" required="true()" type="string"/><bind nodeset="/data/intro/step11" required="true()" type="string"/><bind jr:preload="uid" nodeset="/data/meta/instanceID" readonly="true()" type="string"/></model></h:head><h:body class="pages"><group appearance="field-list" ref="/data/intro"><select1 appearance="label" ref="/data/intro/reserved_name_for_field_list_labels_3"><label> </label><item><label>Done</label><value>done</value></item><item><label>Not Done</label><value>not</value></item></select1><select1 appearance="list-nolabel" ref="/data/intro/step1"><label>Calls out the time of birth and ensures that it is recorded</label><item><label>Done</label><value>done</value></item><item><label>Not Done</label><value>not</value></item></select1><select1 appearance="list-nolabel" ref="/data/intro/step2"><label>Delivers the baby onto a warm, clean towel and keeps on the mothers abdomen</label><item><label>Done</label><value>done</value></item><item><label>Not Done</label><value>not</value></item></select1><select1 appearance="list-nolabel" ref="/data/intro/step3"><label>Immediately dries the baby with same warm clean towel</label><item><label>Done</label><value>done</value></item><item><label>Not Done</label><value>not</value></item></select1><select1 appearance="list-nolabel" ref="/data/intro/step4"><label>Removes the wet towel and wraps the baby in another warm dry towel.</label><item><label>Done</label><value>done</value></item><item><label>Not Done</label><value>not</value></item></select1><select1 appearance="list-nolabel" ref="/data/intro/step5"><label>Assesses the baby's breathing. 

Note: If baby is not breathing/difficulty in breathing initiate resuscitation (ref: Checklist: NBR) 
If baby is breathing normally, rules out twins and administers Inj.Oxytocin, 10 IU, IM (as part of AMTSL</label><item><label>Done</label><value>done</value></item><item><label>Not Done</label><value>not</value></item></select1><select1 appearance="list-nolabel" ref="/data/intro/step6"><label>Wipes both the eyes separately with sterile gauze from medial to lateral side.</label><item><label>Done</label><value>done</value></item><item><label>Not Done</label><value>not</value></item></select1><select1 appearance="list-nolabel" ref="/data/intro/step7"><label>Clamps and cuts the umbilical cord in 1-3 minutes. Checks for any oozing of blood.</label><item><label>Done</label><value>done</value></item><item><label>Not Done</label><value>not</value></item></select1><select1 appearance="list-nolabel" ref="/data/intro/step8"><label>Places an identity label on the baby. Checks for any major congenital malformation</label><item><label>Done</label><value>done</value></item><item><label>Not Done</label><value>not</value></item></select1><select1 appearance="list-nolabel" ref="/data/intro/step9"><label>Leaves the baby in between the mothers breast to initiate skin to skin care</label><item><label>Done</label><value>done</value></item><item><label>Not Done</label><value>not</value></item></select1><select1 appearance="list-nolabel" ref="/data/intro/step10"><label>Covers the baby's head with a cap and covers the mother and baby with a warm cloth/sheet</label><item><label>Done</label><value>done</value></item><item><label>Not Done</label><value>not</value></item></select1><select1 appearance="list-nolabel" ref="/data/intro/step11"><label>Encourages initiation of breast feeding</label><item><label>Done</label><value>done</value></item><item><label>Not Done</label><value>not</value></item></select1></group></h:body></h:html>