<?xml version="1.0"?><h:html xmlns="http://www.w3.org/2002/xforms" xmlns:ev="http://www.w3.org/2001/xml-events" xmlns:h="http://www.w3.org/1999/xhtml" xmlns:jr="http://openrosa.org/javarosa" xmlns:odk="http://www.opendatakit.org/xforms" xmlns:orx="http://openrosa.org/xforms" xmlns:xsd="http://www.w3.org/2001/XMLSchema"><h:head><h:title>OSCE_Suctioning the nasopharyngeal and oropharyngeal airways</h:title><model odk:xforms-version="1.0.0"><instance><data id="osce1_form" version="1.1"><intro><reserved_name_for_field_list_labels_3/><step1/><step2/><step3/><step4/><step5/><step6/><step7/><step8/><step9/><step10/><step11/><step12/><step13/><step14/><step15/><step16/><step17/><step18/><step19/><step20/><step21/><step22/><step23/><step24/><step25/><step26/><step27/><step28/><step29/><step30/></intro><meta><instanceID/></meta></data></instance><bind nodeset="/data/intro/reserved_name_for_field_list_labels_3" type="string"/><bind nodeset="/data/intro/step1" required="true()" type="string"/><bind nodeset="/data/intro/step2" required="true()" type="string"/><bind nodeset="/data/intro/step3" required="true()" type="string"/><bind nodeset="/data/intro/step4" required="true()" type="string"/><bind nodeset="/data/intro/step5" required="true()" type="string"/><bind nodeset="/data/intro/step6" required="true()" type="string"/><bind nodeset="/data/intro/step7" required="true()" type="string"/><bind nodeset="/data/intro/step8" required="true()" type="string"/><bind nodeset="/data/intro/step9" required="true()" type="string"/><bind nodeset="/data/intro/step10" required="true()" type="string"/><bind nodeset="/data/intro/step11" required="true()" type="string"/><bind nodeset="/data/intro/step12" required="true()" type="string"/><bind nodeset="/data/intro/step13" required="true()" type="string"/><bind nodeset="/data/intro/step14" required="true()" type="string"/><bind nodeset="/data/intro/step15" required="true()" type="string"/><bind nodeset="/data/intro/step16" required="true()" type="string"/><bind nodeset="/data/intro/step17" required="true()" type="string"/><bind nodeset="/data/intro/step18" required="true()" type="string"/><bind nodeset="/data/intro/step19" required="true()" type="string"/><bind nodeset="/data/intro/step20" required="true()" type="string"/><bind nodeset="/data/intro/step21" required="true()" type="string"/><bind nodeset="/data/intro/step22" required="true()" type="string"/><bind nodeset="/data/intro/step23" required="true()" type="string"/><bind nodeset="/data/intro/step24" required="true()" type="string"/><bind nodeset="/data/intro/step25" required="true()" type="string"/><bind nodeset="/data/intro/step26" required="true()" type="string"/><bind nodeset="/data/intro/step27" required="true()" type="string"/><bind nodeset="/data/intro/step28" required="true()" type="string"/><bind nodeset="/data/intro/step29" required="true()" type="string"/><bind nodeset="/data/intro/step30" required="true()" type="string"/><bind jr:preload="uid" nodeset="/data/meta/instanceID" readonly="true()" type="string"/></model></h:head><h:body class="pages"><group appearance="field-list" ref="/data/intro"><select1 appearance="label" ref="/data/intro/reserved_name_for_field_list_labels_3"><label> </label><item><label>Done</label><value>done</value></item><item><label>Not Done</label><value>not</value></item></select1><select1 appearance="list-nolabel" ref="/data/intro/step1"><label>Goal: The patient will exhibit improved breath sounds and a clear, patent airway.
Identify the patient.</label><item><label>Done</label><value>done</value></item><item><label>Not Done</label><value>not</value></item></select1><select1 appearance="list-nolabel" ref="/data/intro/step2"><label>Determine the need for suctioning. Verify the suction order in the patient's chart, if necessary. For postoperative patient, administer pain medication before suctioning.</label><item><label>Done</label><value>done</value></item><item><label>Not Done</label><value>not</value></item></select1><select1 appearance="list-nolabel" ref="/data/intro/step3"><label>Explain what you are going to do and the reason to the patient, even if the patient does not appear to be alert. Reassure patient you will interrupt procedure if he or she indicates respiratory difficulty.</label><item><label>Done</label><value>done</value></item><item><label>Not Done</label><value>not</value></item></select1><select1 appearance="list-nolabel" ref="/data/intro/step4"><label>Perform hand hygiene.</label><item><label>Done</label><value>done</value></item><item><label>Not Done</label><value>not</value></item></select1><select1 appearance="list-nolabel" ref="/data/intro/step5"><label>Adjust bed to comfortable working position. Lower side rail closer to you. If patient is conscious, place him or her in a semi-Fowler's position. If patient is unconscious, place him or her in the lateral position, facing you. Move the bed table close to your work area and raise to waist height.</label><item><label>Done</label><value>done</value></item><item><label>Not Done</label><value>not</value></item></select1><select1 appearance="list-nolabel" ref="/data/intro/step6"><label>Place towel or waterproof pad across patient's chest.</label><item><label>Done</label><value>done</value></item><item><label>Not Done</label><value>not</value></item></select1><select1 appearance="list-nolabel" ref="/data/intro/step7"><label>Adjust suction to appropriate pressure:</label><item><label>Done</label><value>done</value></item><item><label>Not Done</label><value>not</value></item></select1><select1 appearance="list-nolabel" ref="/data/intro/step8"><label>For a wall unit for an adult: 100 to 150 mm Hg; neonates: 60 to 80 mm Hg; infants: 80 to 100 mm Hg; children: 100 to 120 mm Hg</label><item><label>Done</label><value>done</value></item><item><label>Not Done</label><value>not</value></item></select1><select1 appearance="list-nolabel" ref="/data/intro/step9"><label>For a portable unit for an adult: 10 to 15 cm Hg; neonates: 6 to 8 cm Hg; infants: 8 to 10 cm Hg; children: 10 to 12 cm Hg</label><item><label>Done</label><value>done</value></item><item><label>Not Done</label><value>not</value></item></select1><select1 appearance="list-nolabel" ref="/data/intro/step10"><label>Put on a disposable, nonsterile glove and occlude the end of the connecting tubing to check suction pressure. Place the connecting tubing in a convenient location.</label><item><label>Done</label><value>done</value></item><item><label>Not Done</label><value>not</value></item></select1><select1 appearance="list-nolabel" ref="/data/intro/step11"><label>Open sterile suction package using aseptic technique. The open wrapper or container becomes a sterile field to hold other supplies. Carefully remove the sterile container, touching only the outside surface. Set it up on the work surface and pour sterile saline into it.</label><item><label>Done</label><value>done</value></item><item><label>Not Done</label><value>not</value></item></select1><select1 appearance="list-nolabel" ref="/data/intro/step12"><label>Place a small amount of water-soluble lubricant on the sterile field, taking care to avoid touching the sterile field with the lubricant package.</label><item><label>Done</label><value>done</value></item><item><label>Not Done</label><value>not</value></item></select1><select1 appearance="list-nolabel" ref="/data/intro/step13"><label>Increase the patient's supplemental oxygen level or apply supplemental oxygen per facility policy or physician order.</label><item><label>Done</label><value>done</value></item><item><label>Not Done</label><value>not</value></item></select1><select1 appearance="list-nolabel" ref="/data/intro/step14"><label>Put on face shield or goggles and mask. Put on sterile gloves. The dominant hand will manipulate the catheter and must remain sterile. The nondominant hand is considered clean rather than sterile and will control the suction valve (Y port) on the catheter.</label><item><label>Done</label><value>done</value></item><item><label>Not Done</label><value>not</value></item></select1><select1 appearance="list-nolabel" ref="/data/intro/step15"><label>With dominant gloved hand, pick up sterile catheter. Pick up the connecting tubing with the nondominant hand and connect the tubing and suction catheter.</label><item><label>Done</label><value>done</value></item><item><label>Not Done</label><value>not</value></item></select1><select1 appearance="list-nolabel" ref="/data/intro/step16"><label>Moisten the catheter by dipping it into the container of sterile saline. Occlude Y-tube to check suction.</label><item><label>Done</label><value>done</value></item><item><label>Not Done</label><value>not</value></item></select1><select1 appearance="list-nolabel" ref="/data/intro/step17"><label>Encourage the patient to take several deep breaths.</label><item><label>Done</label><value>done</value></item><item><label>Not Done</label><value>not</value></item></select1><select1 appearance="list-nolabel" ref="/data/intro/step18"><label>Apply lubricant to the first 2 to 3 inches of the catheter, using the lubricant that was placed on the sterile field.</label><item><label>Done</label><value>done</value></item><item><label>Not Done</label><value>not</value></item></select1><select1 appearance="list-nolabel" ref="/data/intro/step19"><label>Remove the oxygen delivery device, if appropriate. Do not apply suction as the catheter is inserted. Hold the catheter between your thumb and forefinger.</label><item><label>Done</label><value>done</value></item><item><label>Not Done</label><value>not</value></item></select1><select1 appearance="list-nolabel" ref="/data/intro/step20"><label>For nasopharyngeal suctioning: Gently insert catheter through the naris and along the floor of the nostril toward trachea. Roll the catheter between your fingers to help advance it. Advance the catheter approximately 5 to 6 inches to reach the pharynx.</label><item><label>Done</label><value>done</value></item><item><label>Not Done</label><value>not</value></item></select1><select1 appearance="list-nolabel" ref="/data/intro/step21"><label>For oropharyngeal suctioning: Insert catheter through the mouth, along the side of the mouth toward the trachea. Advance the catheter 3 to 4 inches to reach the pharynx.</label><item><label>Done</label><value>done</value></item><item><label>Not Done</label><value>not</value></item></select1><select1 appearance="list-nolabel" ref="/data/intro/step22"><label>Apply suction by intermittently occluding the Y port on the catheter with the thumb of your nondominant hand, and gently rotate the catheter as it is being withdrawn. Do not suction for more than 10 to 15 seconds at a time.</label><item><label>Done</label><value>done</value></item><item><label>Not Done</label><value>not</value></item></select1><select1 appearance="list-nolabel" ref="/data/intro/step23"><label>Replace the oxygen delivery device using your nondominant hand, if appropriate, and have the patient take several deep breaths.</label><item><label>Done</label><value>done</value></item><item><label>Not Done</label><value>not</value></item></select1><select1 appearance="list-nolabel" ref="/data/intro/step24"><label>Flush catheter with saline. Assess effectiveness of suctioning and repeat as needed and according to patient's tolerance.</label><item><label>Done</label><value>done</value></item><item><label>Not Done</label><value>not</value></item></select1><select1 appearance="list-nolabel" ref="/data/intro/step25"><label>Wrap the suction catheter around your dominant hand between attempts.</label><item><label>Done</label><value>done</value></item><item><label>Not Done</label><value>not</value></item></select1><select1 appearance="list-nolabel" ref="/data/intro/step26"><label>Allow at least a 30-second to one-minute interval if additional suctioning is needed. No more than three suction passes should be made per suctioning episode. Alternate the nares, unless contraindicated, if repeated suctioning is required. Do not force catheter through the nares. Encourage patient to cough and deep breathe between suctioning. Suction the oropharynx after suctioning the nasopharynx.</label><item><label>Done</label><value>done</value></item><item><label>Not Done</label><value>not</value></item></select1><select1 appearance="list-nolabel" ref="/data/intro/step27"><label>When suctioning is completed, remove gloves from dominant hand over the coiled catheter, pulling it off inside out. Remove glove from nondominant hand and dispose of gloves, catheter, and container with solution in the appropriate receptacle. Remove face shield or goggles and mask. Perform hand hygiene.</label><item><label>Done</label><value>done</value></item><item><label>Not Done</label><value>not</value></item></select1><select1 appearance="list-nolabel" ref="/data/intro/step28"><label>Turn off suction. Remove supplemental oxygen placed for suctioning, if appropriate. Assist patient to a comfortable position. Raise bed rail.</label><item><label>Done</label><value>done</value></item><item><label>Not Done</label><value>not</value></item></select1><select1 appearance="list-nolabel" ref="/data/intro/step29"><label>Offer oral hygiene after suctioning.</label><item><label>Done</label><value>done</value></item><item><label>Not Done</label><value>not</value></item></select1><select1 appearance="list-nolabel" ref="/data/intro/step30"><label>Reassess patient's respiratory status, including respiratory rate, effort, oxygen saturation, and lung sounds.</label><item><label>Done</label><value>done</value></item><item><label>Not Done</label><value>not</value></item></select1></group></h:body></h:html>